rtl/Hossam/shift_reg.v
module shift_reg (
    input  wire       scl,
    input  wire       rst,
    input  wire [7:0] data_in,
    input  wire       sda_in,
    input  wire       direction,
    input  wire       enable,
    input  wire       load,
    output reg  [7:0] data_out,
    output reg        rx_done,
    output reg        tx_done,
    output reg        sda_out
);

reg [7:0] tx_buffer;
reg [2:0] bit_count;

always @(posedge scl or negedge rst) begin
    if (!rst) begin
        data_out  <= 0;
        sda_out   <= 0;
        tx_buffer <= 0;
        rx_done   <= 0;
        tx_done   <= 0;
        bit_count <= 0;
    end
    else if (enable) begin
        rx_done <= 0;
        tx_done <= 0;

        if (!direction) begin // receive
            data_out <= {data_out[6:0], sda_in};
            if (bit_count == 3'b111) begin
                rx_done   <= 1;
                bit_count <= 0;
            end
            else begin
                bit_count <= bit_count + 1;
            end
        end
        else begin // transmit
            if (load) begin
                tx_buffer <= data_in;
                bit_count <= 0;
            end
            else begin
                sda_out   <= tx_buffer[7];
                tx_buffer <= {tx_buffer[6:0], 1'b0};
                if (bit_count == 3'b111) begin
                    tx_done   <= 1;
                    bit_count <= 0;
                end
                else begin
                    bit_count <= bit_count + 1;
                end
            end
        end
    end
end

endmodule

rtl/Hossam/clock_generator.v
module clock_generator (
    input  wire       sys_clk,
    input  wire       rst,
    input  wire       enable,
    input  wire [7:0] div_value,
    output reg        scl
);

reg [7:0] counter;

always @(posedge sys_clk or negedge rst) begin
    if (!rst) begin
        counter <= 0;
        scl     <= 0;
    end
    else if (enable) begin
        counter <= counter + 1;
        if (counter == div_value >> 1) begin
            scl     <= ~scl;
            counter <= 0;
        end
    end
end

endmodule

rtl/Hossam/i2c_fsm.v
module i2c_fsm (
    input  wire       sys_clk,   
    input  wire       scl,                     
    input  wire       rst,
    input  wire       rx_done,
    input  wire       tx_done,
    input  wire [7:0] data_rx,
    input  wire       start,
    input  wire       rw_mode,   

    output reg        direction,
    output reg        enable,
    output reg        load,
    output reg        ack,
    output reg        nack,
    output wire       busy       
);

reg [3:0] current_state, next_state;

localparam IDLE        = 4'b0000;
localparam START       = 4'b0001;
localparam ADDRESS     = 4'b0010;
localparam ACK_ADDR    = 4'b0011;
localparam DATA_TX     = 4'b0100;
localparam ACK_DATA_TX = 4'b0101;
localparam DATA_RX     = 4'b0110;
localparam ACK_DATA_RX = 4'b0111;
localparam STOP        = 4'b1000;
)
assign busy = (current_state != IDLE);


// State register
always @(posedge sys_clk or negedge rst) begin
    if (!rst)
        current_state <= IDLE;
    else
        current_state <= next_state;
end

reg [3:0] state_scl_sync;

always @(posedge scl or negedge rst) begin
    if (!rst)
        state_scl_sync <= IDLE;
    else
        state_scl_sync <= current_state;
end

// Next-state logic
always @(*) begin
    case (current_state)
        IDLE        : next_state = start   ? START      : IDLE;
        START       : next_state = ADDRESS;
        ADDRESS     : next_state = tx_done ? ACK_ADDR    : ADDRESS;
        ACK_ADDR    : next_state = rw_mode ? DATA_TX     : DATA_RX;
        DATA_TX     : next_state = tx_done ? ACK_DATA_TX : DATA_TX;
        ACK_DATA_TX : next_state = STOP;
        DATA_RX     : next_state = rx_done ? ACK_DATA_RX : DATA_RX;
        ACK_DATA_RX : next_state = STOP;
        STOP        : next_state = IDLE;
        default     : next_state = IDLE;
    endcase
end

always @(*) begin
    direction = 0;
    enable    = 0;
    load      = 0;
    ack       = 0;
    nack      = 0;

    case (current_state)
        IDLE: enable = 0;

        START: enable = 1;

        ADDRESS: begin
            enable    = 1;
            direction = 1;
            if (state_scl_sync != ADDRESS)
                load = 1;
            else
                load = 0;
        end

        ACK_ADDR: begin
            enable    = 1;
            direction = 0;
        end

        DATA_TX: begin
            enable    = 1;
            direction = 1;
            if (state_scl_sync != DATA_TX)
                load = 1;
            else
                load = 0;
        end

        ACK_DATA_TX: begin
            enable    = 1;
            direction = 0;
        end

        DATA_RX: begin
            enable    = 1;
            direction = 0;
        end

        ACK_DATA_RX: begin
            enable    = 1;
            direction = 1;
            ack       = 1;
        end

        STOP: enable = 0;
    endcase
end

endmodule

rtl/Hossam/register_file.v


module register_file (
    input  wire       pclk,
    input  wire       presetn,
    input  wire       write_enable,
    input  wire       read_enable,
    input  wire [7:0] address,
    input  wire [7:0] wdata,
    output reg  [7:0] rdata,

  
    output reg  [7:0] div_value,
    output reg  [7:0] data_tx,
    output reg        start,
    output reg        rw_mode,


    input  wire [7:0] data_rx,
    input  wire       ack,
    input  wire       nack,
    input  wire       busy
);

localparam ADDR_DIV_VALUE = 8'h00;
localparam ADDR_DATA_TX   = 8'h01;
localparam ADDR_DATA_RX   = 8'h02;
localparam ADDR_START     = 8'h03;
localparam ADDR_RW_MODE   = 8'h04;
localparam ADDR_STATUS    = 8'h05;


always @(posedge pclk or negedge presetn) begin
    if (!presetn) begin
        div_value <= 8'h00;
        data_tx   <= 8'h00;
        start     <= 1'b0;
        rw_mode   <= 1'b0;
    end
    else begin
       
        start <= 1'b0;

        if (write_enable) begin
            case (address)
                ADDR_DIV_VALUE: div_value <= wdata;
                ADDR_DATA_TX:   data_tx   <= wdata;
                ADDR_START:     start     <= wdata[0];
                ADDR_RW_MODE:   rw_mode   <= wdata[0];
                default: ; 
            endcase
        end
    end
end

// Read logic
always @(*) begin
    case (address)
        ADDR_DIV_VALUE: rdata = div_value;
        ADDR_DATA_TX:   rdata = data_tx;
        ADDR_DATA_RX:   rdata = data_rx;
        ADDR_RW_MODE:   rdata = {7'b0, rw_mode};
        ADDR_STATUS:    rdata = {5'b0, busy, nack, ack};
        default:        rdata = 8'h00;
    endcase
end

endmodule

rtl/Hossam/APB_interface.v
module apb_interface (
    input  wire        PCLK,
    input  wire        PRST_n,
    input  wire        PSEL_i2c,
    input  wire        PEN,
    input  wire        PWRITE,
    input  wire [31:0] PADDR,
    input  wire [31:0] PWDATA,
    output reg  [31:0] PRDATA_I2C,
    output reg         PREADY_i2c,

    output reg         write_enable,
    output reg         read_enable,
    output reg  [7:0]  address,
    output reg  [7:0]  wdata,
    input  wire [7:0]  rdata
);

wire access = PSEL_i2c & PEN;

always @(*) begin
    write_enable = access & PWRITE;
    read_enable  = access & ~PWRITE;
    address      = PADDR[7:0];   
    wdata        = PWDATA[7:0];
end

always @(*) begin
    PREADY_i2c = access;
end

always @(*) begin
    PRDATA_I2C = {24'b0, rdata};
end

endmodule

rtl/Hossam/i2c_top.v

module i2c_top (
  
    input  wire        PCLK,
    input  wire        PRST_n,
    input  wire        PSEL_i2c,
    input  wire        PEN,
    input  wire        PWRITE,
    input  wire [31:0] PADDR,
    input  wire [31:0] PWDATA,
    output wire [31:0] PRDATA_I2C,
    output wire        PREADY_i2c,

   
    input  wire         sda_in,
    output wire          sda_out
);


wire        write_enable, read_enable;
wire [7:0]  reg_address, reg_wdata, reg_rdata;

wire [7:0]  div_value;
wire [7:0]  data_tx;
wire        start;
wire        rw_mode;
wire [7:0]  data_rx;
wire        ack, nack, busy;

wire        direction, enable, load;
wire        scl;
wire        tx_done, rx_done;

// --- APB interface ---
apb_interface u_apb_interface (
    .PCLK        (PCLK),
    .PRST_n      (PRST_n),
    .PSEL_i2c    (PSEL_i2c),
    .PEN         (PEN),
    .PWRITE      (PWRITE),
    .PADDR       (PADDR),
    .PWDATA      (PWDATA),
    .PRDATA_I2C  (PRDATA_I2C),
    .PREADY_i2c  (PREADY_i2c),
    .write_enable(write_enable),
    .read_enable (read_enable),
    .address     (reg_address),
    .wdata       (reg_wdata),
    .rdata       (reg_rdata)
);

// --- Register file ---
register_file u_register_file (
    .pclk        (PCLK),
    .presetn     (PRST_n),
    .write_enable(write_enable),
    .read_enable (read_enable),
    .address     (reg_address),
    .wdata       (reg_wdata),
    .rdata       (reg_rdata),
    .div_value   (div_value),
    .data_tx     (data_tx),
    .start       (start),
    .rw_mode     (rw_mode),
    .data_rx     (data_rx),
    .ack         (ack),
    .nack        (nack),
    .busy        (busy)
);

// --- FSM controller (main logic on PCLK; load pulse synced via scl) ---
i2c_fsm u_i2c_fsm (
    .sys_clk   (PCLK),
    .scl       (scl),
    .rst       (PRST_n),
    .rx_done   (rx_done),
    .tx_done   (tx_done),
    .data_rx   (data_rx),
    .start     (start),
    .rw_mode   (rw_mode),
    .direction (direction),
    .enable    (enable),
    .load      (load),
    .ack       (ack),
    .nack      (nack),
    .busy      (busy)
);

// --- Clock generator (drives SCL) ---
clock_generator u_clock_generator (
    .sys_clk  (PCLK),
    .rst      (PRST_n),
    .enable   (enable),
    .div_value(div_value),
    .scl      (scl)
);

// --- Shift register (drives/samples SDA) ---
shift_reg u_shift_reg (
    .scl      (scl),
    .rst      (PRST_n),
    .data_in  (data_tx),
    .sda_in   (sda_in),
    .direction(direction),
    .enable   (enable),
    .load     (load),
    .data_out (data_rx),
    .rx_done  (rx_done),
    .tx_done  (tx_done),
    .sda_out  (sda_out)
);

endmodule

rtl/Hossam/i2c_top_sanity_tb.v
`timescale 1ns/1ps
module i2c_top_sanity_tb;

reg         PCLK, PRST_n;
reg         PSEL_i2c, PEN, PWRITE;
reg  [31:0] PADDR, PWDATA;
wire [31:0] PRDATA_I2C;
wire        PREADY_i2c;
reg         sda_in;
wire        sda_out;

i2c_top dut (
    .PCLK      (PCLK),
    .PRST_n    (PRST_n),
    .PSEL_i2c  (PSEL_i2c),
    .PEN       (PEN),
    .PWRITE    (PWRITE),
    .PADDR     (PADDR),
    .PWDATA    (PWDATA),
    .PRDATA_I2C(PRDATA_I2C),
    .PREADY_i2c(PREADY_i2c),
    .sda_in    (sda_in),
    .sda_out   (sda_out)
);

always #5 PCLK = ~PCLK;

// simple APB write task
task apb_write(input [7:0] addr, input [7:0] data);
begin
    @(posedge PCLK);
    PSEL_i2c = 1; PWRITE = 1; PADDR = addr; PWDATA = data; PEN = 0;
    @(posedge PCLK);
    PEN = 1;
    @(posedge PCLK);
    PSEL_i2c = 0; PEN = 0;
end
endtask

initial begin
    PCLK     = 0;
    PRST_n   = 0;
    PSEL_i2c = 0;
    PEN      = 0;
    PWRITE   = 0;
    PADDR    = 0;
    PWDATA   = 0;
    sda_in   = 0;

    #12 PRST_n = 1;

    
    apb_write(8'h00, 8'd8);     
    apb_write(8'h01, 8'hA5);    
    apb_write(8'h04, 8'h01);    
    apb_write(8'h03, 8'h01);    

    #2000 $finish;
end

initial begin
    $dumpfile("i2c_top_sanity.vcd");
    $dumpvars(0, i2c_top_sanity_tb);
end

endmodule

rtl/Hossam/i2c_top_sanity.vcd
$date
	Mon Sep 07 09:37:35 2026
$end
$version
	ModelSim Version 10.1d
$end
$timescale
	1ps
$end
$scope module i2c_top_sanity_tb $end
$var reg 1 ! PCLK $end
$var reg 1 " PRST_n $end
$var reg 1 # PSEL_i2c $end
$var reg 1 $ PEN $end
$var reg 1 % PWRITE $end
$var reg 32 & PADDR [31:0] $end
$var reg 32 ' PWDATA [31:0] $end
$var wire 1 ( PRDATA_I2C [31] $end
$var wire 1 ) PRDATA_I2C [30] $end
$var wire 1 * PRDATA_I2C [29] $end
$var wire 1 + PRDATA_I2C [28] $end
$var wire 1 , PRDATA_I2C [27] $end
$var wire 1 - PRDATA_I2C [26] $end
$var wire 1 . PRDATA_I2C [25] $end
$var wire 1 / PRDATA_I2C [24] $end
$var wire 1 0 PRDATA_I2C [23] $end
$var wire 1 1 PRDATA_I2C [22] $end
$var wire 1 2 PRDATA_I2C [21] $end
$var wire 1 3 PRDATA_I2C [20] $end
$var wire 1 4 PRDATA_I2C [19] $end
$var wire 1 5 PRDATA_I2C [18] $end
$var wire 1 6 PRDATA_I2C [17] $end
$var wire 1 7 PRDATA_I2C [16] $end
$var wire 1 8 PRDATA_I2C [15] $end
$var wire 1 9 PRDATA_I2C [14] $end
$var wire 1 : PRDATA_I2C [13] $end
$var wire 1 ; PRDATA_I2C [12] $end
$var wire 1 < PRDATA_I2C [11] $end
$var wire 1 = PRDATA_I2C [10] $end
$var wire 1 > PRDATA_I2C [9] $end
$var wire 1 ? PRDATA_I2C [8] $end
$var wire 1 @ PRDATA_I2C [7] $end
$var wire 1 A PRDATA_I2C [6] $end
$var wire 1 B PRDATA_I2C [5] $end
$var wire 1 C PRDATA_I2C [4] $end
$var wire 1 D PRDATA_I2C [3] $end
$var wire 1 E PRDATA_I2C [2] $end
$var wire 1 F PRDATA_I2C [1] $end
$var wire 1 G PRDATA_I2C [0] $end
$var wire 1 H PREADY_i2c $end
$var reg 1 I sda_in $end
$var wire 1 J sda_out $end
$scope task apb_write $end
$var reg 8 K addr [7:0] $end
$var reg 8 L data [7:0] $end
$upscope $end
$scope module dut $end
$var wire 1 M PCLK $end
$var wire 1 N PRST_n $end
$var wire 1 O PSEL_i2c $end
$var wire 1 P PEN $end
$var wire 1 Q PWRITE $end
$var wire 1 R PADDR [31] $end
$var wire 1 S PADDR [30] $end
$var wire 1 T PADDR [29] $end
$var wire 1 U PADDR [28] $end
$var wire 1 V PADDR [27] $end
$var wire 1 W PADDR [26] $end
$var wire 1 X PADDR [25] $end
$var wire 1 Y PADDR [24] $end
$var wire 1 Z PADDR [23] $end
$var wire 1 [ PADDR [22] $end
$var wire 1 \ PADDR [21] $end
$var wire 1 ] PADDR [20] $end
$var wire 1 ^ PADDR [19] $end
$var wire 1 _ PADDR [18] $end
$var wire 1 ` PADDR [17] $end
$var wire 1 a PADDR [16] $end
$var wire 1 b PADDR [15] $end
$var wire 1 c PADDR [14] $end
$var wire 1 d PADDR [13] $end
$var wire 1 e PADDR [12] $end
$var wire 1 f PADDR [11] $end
$var wire 1 g PADDR [10] $end
$var wire 1 h PADDR [9] $end
$var wire 1 i PADDR [8] $end
$var wire 1 j PADDR [7] $end
$var wire 1 k PADDR [6] $end
$var wire 1 l PADDR [5] $end
$var wire 1 m PADDR [4] $end
$var wire 1 n PADDR [3] $end
$var wire 1 o PADDR [2] $end
$var wire 1 p PADDR [1] $end
$var wire 1 q PADDR [0] $end
$var wire 1 r PWDATA [31] $end
$var wire 1 s PWDATA [30] $end
$var wire 1 t PWDATA [29] $end
$var wire 1 u PWDATA [28] $end
$var wire 1 v PWDATA [27] $end
$var wire 1 w PWDATA [26] $end
$var wire 1 x PWDATA [25] $end
$var wire 1 y PWDATA [24] $end
$var wire 1 z PWDATA [23] $end
$var wire 1 { PWDATA [22] $end
$var wire 1 | PWDATA [21] $end
$var wire 1 } PWDATA [20] $end
$var wire 1 ~ PWDATA [19] $end
$var wire 1 !! PWDATA [18] $end
$var wire 1 "! PWDATA [17] $end
$var wire 1 #! PWDATA [16] $end
$var wire 1 $! PWDATA [15] $end
$var wire 1 %! PWDATA [14] $end
$var wire 1 &! PWDATA [13] $end
$var wire 1 '! PWDATA [12] $end
$var wire 1 (! PWDATA [11] $end
$var wire 1 )! PWDATA [10] $end
$var wire 1 *! PWDATA [9] $end
$var wire 1 +! PWDATA [8] $end
$var wire 1 ,! PWDATA [7] $end
$var wire 1 -! PWDATA [6] $end
$var wire 1 .! PWDATA [5] $end
$var wire 1 /! PWDATA [4] $end
$var wire 1 0! PWDATA [3] $end
$var wire 1 1! PWDATA [2] $end
$var wire 1 2! PWDATA [1] $end
$var wire 1 3! PWDATA [0] $end
$var wire 1 ( PRDATA_I2C [31] $end
$var wire 1 ) PRDATA_I2C [30] $end
$var wire 1 * PRDATA_I2C [29] $end
$var wire 1 + PRDATA_I2C [28] $end
$var wire 1 , PRDATA_I2C [27] $end
$var wire 1 - PRDATA_I2C [26] $end
$var wire 1 . PRDATA_I2C [25] $end
$var wire 1 / PRDATA_I2C [24] $end
$var wire 1 0 PRDATA_I2C [23] $end
$var wire 1 1 PRDATA_I2C [22] $end
$var wire 1 2 PRDATA_I2C [21] $end
$var wire 1 3 PRDATA_I2C [20] $end
$var wire 1 4 PRDATA_I2C [19] $end
$var wire 1 5 PRDATA_I2C [18] $end
$var wire 1 6 PRDATA_I2C [17] $end
$var wire 1 7 PRDATA_I2C [16] $end
$var wire 1 8 PRDATA_I2C [15] $end
$var wire 1 9 PRDATA_I2C [14] $end
$var wire 1 : PRDATA_I2C [13] $end
$var wire 1 ; PRDATA_I2C [12] $end
$var wire 1 < PRDATA_I2C [11] $end
$var wire 1 = PRDATA_I2C [10] $end
$var wire 1 > PRDATA_I2C [9] $end
$var wire 1 ? PRDATA_I2C [8] $end
$var wire 1 @ PRDATA_I2C [7] $end
$var wire 1 A PRDATA_I2C [6] $end
$var wire 1 B PRDATA_I2C [5] $end
$var wire 1 C PRDATA_I2C [4] $end
$var wire 1 D PRDATA_I2C [3] $end
$var wire 1 E PRDATA_I2C [2] $end
$var wire 1 F PRDATA_I2C [1] $end
$var wire 1 G PRDATA_I2C [0] $end
$var wire 1 H PREADY_i2c $end
$var wire 1 4! sda_in $end
$var wire 1 J sda_out $end
$var wire 1 5! write_enable $end
$var wire 1 6! read_enable $end
$var wire 1 7! reg_address [7] $end
$var wire 1 8! reg_address [6] $end
$var wire 1 9! reg_address [5] $end
$var wire 1 :! reg_address [4] $end
$var wire 1 ;! reg_address [3] $end
$var wire 1 <! reg_address [2] $end
$var wire 1 =! reg_address [1] $end
$var wire 1 >! reg_address [0] $end
$var wire 1 ?! reg_wdata [7] $end
$var wire 1 @! reg_wdata [6] $end
$var wire 1 A! reg_wdata [5] $end
$var wire 1 B! reg_wdata [4] $end
$var wire 1 C! reg_wdata [3] $end
$var wire 1 D! reg_wdata [2] $end
$var wire 1 E! reg_wdata [1] $end
$var wire 1 F! reg_wdata [0] $end
$var wire 1 G! reg_rdata [7] $end
$var wire 1 H! reg_rdata [6] $end
$var wire 1 I! reg_rdata [5] $end
$var wire 1 J! reg_rdata [4] $end
$var wire 1 K! reg_rdata [3] $end
$var wire 1 L! reg_rdata [2] $end
$var wire 1 M! reg_rdata [1] $end
$var wire 1 N! reg_rdata [0] $end
$var wire 1 O! div_value [7] $end
$var wire 1 P! div_value [6] $end
$var wire 1 Q! div_value [5] $end
$var wire 1 R! div_value [4] $end
$var wire 1 S! div_value [3] $end
$var wire 1 T! div_value [2] $end
$var wire 1 U! div_value [1] $end
$var wire 1 V! div_value [0] $end
$var wire 1 W! data_tx [7] $end
$var wire 1 X! data_tx [6] $end
$var wire 1 Y! data_tx [5] $end
$var wire 1 Z! data_tx [4] $end
$var wire 1 [! data_tx [3] $end
$var wire 1 \! data_tx [2] $end
$var wire 1 ]! data_tx [1] $end
$var wire 1 ^! data_tx [0] $end
$var wire 1 _! start $end
$var wire 1 `! rw_mode $end
$var wire 1 a! data_rx [7] $end
$var wire 1 b! data_rx [6] $end
$var wire 1 c! data_rx [5] $end
$var wire 1 d! data_rx [4] $end
$var wire 1 e! data_rx [3] $end
$var wire 1 f! data_rx [2] $end
$var wire 1 g! data_rx [1] $end
$var wire 1 h! data_rx [0] $end
$var wire 1 i! ack $end
$var wire 1 j! nack $end
$var wire 1 k! busy $end
$var wire 1 l! direction $end
$var wire 1 m! enable $end
$var wire 1 n! load $end
$var wire 1 o! scl $end
$var wire 1 p! tx_done $end
$var wire 1 q! rx_done $end
$scope module u_apb_interface $end
$var wire 1 M PCLK $end
$var wire 1 N PRST_n $end
$var wire 1 O PSEL_i2c $end
$var wire 1 P PEN $end
$var wire 1 Q PWRITE $end
$var wire 1 R PADDR [31] $end
$var wire 1 S PADDR [30] $end
$var wire 1 T PADDR [29] $end
$var wire 1 U PADDR [28] $end
$var wire 1 V PADDR [27] $end
$var wire 1 W PADDR [26] $end
$var wire 1 X PADDR [25] $end
$var wire 1 Y PADDR [24] $end
$var wire 1 Z PADDR [23] $end
$var wire 1 [ PADDR [22] $end
$var wire 1 \ PADDR [21] $end
$var wire 1 ] PADDR [20] $end
$var wire 1 ^ PADDR [19] $end
$var wire 1 _ PADDR [18] $end
$var wire 1 ` PADDR [17] $end
$var wire 1 a PADDR [16] $end
$var wire 1 b PADDR [15] $end
$var wire 1 c PADDR [14] $end
$var wire 1 d PADDR [13] $end
$var wire 1 e PADDR [12] $end
$var wire 1 f PADDR [11] $end
$var wire 1 g PADDR [10] $end
$var wire 1 h PADDR [9] $end
$var wire 1 i PADDR [8] $end
$var wire 1 j PADDR [7] $end
$var wire 1 k PADDR [6] $end
$var wire 1 l PADDR [5] $end
$var wire 1 m PADDR [4] $end
$var wire 1 n PADDR [3] $end
$var wire 1 o PADDR [2] $end
$var wire 1 p PADDR [1] $end
$var wire 1 q PADDR [0] $end
$var wire 1 r PWDATA [31] $end
$var wire 1 s PWDATA [30] $end
$var wire 1 t PWDATA [29] $end
$var wire 1 u PWDATA [28] $end
$var wire 1 v PWDATA [27] $end
$var wire 1 w PWDATA [26] $end
$var wire 1 x PWDATA [25] $end
$var wire 1 y PWDATA [24] $end
$var wire 1 z PWDATA [23] $end
$var wire 1 { PWDATA [22] $end
$var wire 1 | PWDATA [21] $end
$var wire 1 } PWDATA [20] $end
$var wire 1 ~ PWDATA [19] $end
$var wire 1 !! PWDATA [18] $end
$var wire 1 "! PWDATA [17] $end
$var wire 1 #! PWDATA [16] $end
$var wire 1 $! PWDATA [15] $end
$var wire 1 %! PWDATA [14] $end
$var wire 1 &! PWDATA [13] $end
$var wire 1 '! PWDATA [12] $end
$var wire 1 (! PWDATA [11] $end
$var wire 1 )! PWDATA [10] $end
$var wire 1 *! PWDATA [9] $end
$var wire 1 +! PWDATA [8] $end
$var wire 1 ,! PWDATA [7] $end
$var wire 1 -! PWDATA [6] $end
$var wire 1 .! PWDATA [5] $end
$var wire 1 /! PWDATA [4] $end
$var wire 1 0! PWDATA [3] $end
$var wire 1 1! PWDATA [2] $end
$var wire 1 2! PWDATA [1] $end
$var wire 1 3! PWDATA [0] $end
$var reg 32 r! PRDATA_I2C [31:0] $end
$var reg 1 s! PREADY_i2c $end
$var reg 1 t! write_enable $end
$var reg 1 u! read_enable $end
$var reg 8 v! address [7:0] $end
$var reg 8 w! wdata [7:0] $end
$var wire 1 G! rdata [7] $end
$var wire 1 H! rdata [6] $end
$var wire 1 I! rdata [5] $end
$var wire 1 J! rdata [4] $end
$var wire 1 K! rdata [3] $end
$var wire 1 L! rdata [2] $end
$var wire 1 M! rdata [1] $end
$var wire 1 N! rdata [0] $end
$var wire 1 x! access $end
$upscope $end
$scope module u_register_file $end
$var parameter 8 y! ADDR_DIV_VALUE $end
$var parameter 8 z! ADDR_DATA_TX $end
$var parameter 8 {! ADDR_DATA_RX $end
$var parameter 8 |! ADDR_START $end
$var parameter 8 }! ADDR_RW_MODE $end
$var parameter 8 ~! ADDR_STATUS $end
$var wire 1 M pclk $end
$var wire 1 N presetn $end
$var wire 1 5! write_enable $end
$var wire 1 6! read_enable $end
$var wire 1 7! address [7] $end
$var wire 1 8! address [6] $end
$var wire 1 9! address [5] $end
$var wire 1 :! address [4] $end
$var wire 1 ;! address [3] $end
$var wire 1 <! address [2] $end
$var wire 1 =! address [1] $end
$var wire 1 >! address [0] $end
$var wire 1 ?! wdata [7] $end
$var wire 1 @! wdata [6] $end
$var wire 1 A! wdata [5] $end
$var wire 1 B! wdata [4] $end
$var wire 1 C! wdata [3] $end
$var wire 1 D! wdata [2] $end
$var wire 1 E! wdata [1] $end
$var wire 1 F! wdata [0] $end
$var reg 8 !" rdata [7:0] $end
$var reg 8 "" div_value [7:0] $end
$var reg 8 #" data_tx [7:0] $end
$var reg 1 $" start $end
$var reg 1 %" rw_mode $end
$var wire 1 a! data_rx [7] $end
$var wire 1 b! data_rx [6] $end
$var wire 1 c! data_rx [5] $end
$var wire 1 d! data_rx [4] $end
$var wire 1 e! data_rx [3] $end
$var wire 1 f! data_rx [2] $end
$var wire 1 g! data_rx [1] $end
$var wire 1 h! data_rx [0] $end
$var wire 1 i! ack $end
$var wire 1 j! nack $end
$var wire 1 k! busy $end
$upscope $end
$scope module u_i2c_fsm $end
$var parameter 4 &" IDLE $end
$var parameter 4 '" START $end
$var parameter 4 (" ADDRESS $end
$var parameter 4 )" ACK_ADDR $end
$var parameter 4 *" DATA_TX $end
$var parameter 4 +" ACK_DATA_TX $end
$var parameter 4 ," DATA_RX $end
$var parameter 4 -" ACK_DATA_RX $end
$var parameter 4 ." STOP $end
$var wire 1 M sys_clk $end
$var wire 1 o! scl $end
$var wire 1 N rst $end
$var wire 1 q! rx_done $end
$var wire 1 p! tx_done $end
$var wire 1 a! data_rx [7] $end
$var wire 1 b! data_rx [6] $end
$var wire 1 c! data_rx [5] $end
$var wire 1 d! data_rx [4] $end
$var wire 1 e! data_rx [3] $end
$var wire 1 f! data_rx [2] $end
$var wire 1 g! data_rx [1] $end
$var wire 1 h! data_rx [0] $end
$var wire 1 _! start $end
$var wire 1 `! rw_mode $end
$var reg 1 /" direction $end
$var reg 1 0" enable $end
$var reg 1 1" load $end
$var reg 1 2" ack $end
$var reg 1 3" nack $end
$var wire 1 k! busy $end
$var reg 4 4" current_state [3:0] $end
$var reg 4 5" next_state [3:0] $end
$var reg 4 6" state_scl_sync [3:0] $end
$upscope $end
$scope module u_clock_generator $end
$var wire 1 M sys_clk $end
$var wire 1 N rst $end
$var wire 1 m! enable $end
$var wire 1 O! div_value [7] $end
$var wire 1 P! div_value [6] $end
$var wire 1 Q! div_value [5] $end
$var wire 1 R! div_value [4] $end
$var wire 1 S! div_value [3] $end
$var wire 1 T! div_value [2] $end
$var wire 1 U! div_value [1] $end
$var wire 1 V! div_value [0] $end
$var reg 1 7" scl $end
$var reg 8 8" counter [7:0] $end
$upscope $end
$scope module u_shift_reg $end
$var wire 1 o! scl $end
$var wire 1 N rst $end
$var wire 1 W! data_in [7] $end
$var wire 1 X! data_in [6] $end
$var wire 1 Y! data_in [5] $end
$var wire 1 Z! data_in [4] $end
$var wire 1 [! data_in [3] $end
$var wire 1 \! data_in [2] $end
$var wire 1 ]! data_in [1] $end
$var wire 1 ^! data_in [0] $end
$var wire 1 4! sda_in $end
$var wire 1 l! direction $end
$var wire 1 m! enable $end
$var wire 1 n! load $end
$var reg 8 9" data_out [7:0] $end
$var reg 1 :" rx_done $end
$var reg 1 ;" tx_done $end
$var reg 1 <" sda_out $end
$var reg 8 =" tx_buffer [7:0] $end
$var reg 3 >" bit_count [2:0] $end
$upscope $end
$upscope $end
$upscope $end
$enddefinitions $end
#0
$dumpvars
0!
0"
0#
0$
0%
b0 &
b0 '
0I
b0 r!
0s!
0t!
0u!
b0 v!
b0 w!
b0 !"
b0 ""
b0 #"
0$"
0%"
0/"
00"
01"
02"
03"
b0 4"
b0 5"
b0 6"
07"
b0 8"
b0 9"
0:"
0;"
0<"
b0 ="
b0 >"
bx K
bx L
b0 y!
b1 z!
b10 {!
b11 |!
b100 }!
b101 ~!
b0 &"
b1 '"
b10 ("
b11 )"
b100 *"
b101 +"
b110 ,"
b111 -"
b1000 ."
0G
0F
0E
0D
0C
0B
0A
0@
0?
0>
0=
0<
0;
0:
09
08
07
06
05
04
03
02
01
00
0/
0.
0-
0,
0+
0*
0)
0(
0H
0J
05!
06!
0>!
0=!
0<!
0;!
0:!
09!
08!
07!
0F!
0E!
0D!
0C!
0B!
0A!
0@!
0?!
0N!
0M!
0L!
0K!
0J!
0I!
0H!
0G!
0V!
0U!
0T!
0S!
0R!
0Q!
0P!
0O!
0^!
0]!
0\!
0[!
0Z!
0Y!
0X!
0W!
0_!
0`!
0h!
0g!
0f!
0e!
0d!
0c!
0b!
0a!
0i!
0j!
0k!
0l!
0m!
0n!
0o!
0p!
0q!
0x!
04!
03!
02!
01!
00!
0/!
0.!
0-!
0,!
0+!
0*!
0)!
0(!
0'!
0&!
0%!
0$!
0#!
0"!
0!!
0~
0}
0|
0{
0z
0y
0x
0w
0v
0u
0t
0s
0r
0q
0p
0o
0n
0m
0l
0k
0j
0i
0h
0g
0f
0e
0d
0c
0b
0a
0`
0_
0^
0]
0\
0[
0Z
0Y
0X
0W
0V
0U
0T
0S
0R
0Q
0P
0O
0N
0M
$end
#5000
1!
1M
#10000
0!
0M
#12000
1"
b0 K
b1000 L
1N
#15000
1!
1M
1#
1%
b1000 '
1O
1Q
10!
b1000 w!
1C!
#20000
0!
0M
#25000
1!
1M
1$
1P
1x!
1t!
1s!
15!
1H
#30000
0!
0M
#35000
1!
1M
0#
0$
b1 K
b10100101 L
0O
0P
0x!
0t!
0s!
05!
0H
b1000 ""
1S!
b1000 !"
1K!
b1000 r!
1D
#40000
0!
0M
#45000
1!
1M
1#
b1 &
b10100101 '
1O
13!
11!
00!
1.!
1,!
1q
b1 v!
b10100101 w!
1F!
1D!
0C!
1A!
1?!
1>!
b0 !"
0K!
b0 r!
0D
#50000
0!
0M
#55000
1!
1M
1$
1P
1x!
1t!
1s!
15!
1H
#60000
0!
0M
#65000
1!
1M
0#
0$
b100 K
b1 L
0O
0P
0x!
0t!
0s!
05!
0H
b10100101 #"
1^!
1\!
1Y!
1W!
b10100101 !"
1N!
1L!
1I!
1G!
b10100101 r!
1G
1E
1B
1@
#70000
0!
0M
#75000
1!
1M
1#
b100 &
b1 '
1O
01!
0.!
0,!
0q
1o
b100 v!
b1 w!
0D!
0A!
0?!
0>!
1<!
b0 !"
0N!
0L!
0I!
0G!
b0 r!
0G
0E
0B
0@
#80000
0!
0M
#85000
1!
1M
1$
1P
1x!
1t!
1s!
15!
1H
#90000
0!
0M
#95000
1!
1M
0#
0$
b11 K
0O
0P
0x!
0t!
0s!
05!
0H
1%"
1`!
b1 !"
1N!
b1 r!
1G
#100000
0!
0M
#105000
1!
1M
1#
b11 &
1O
1q
1p
0o
b11 v!
1>!
1=!
0<!
b0 !"
0N!
b0 r!
0G
#110000
0!
0M
#115000
1!
1M
1$
1P
1x!
1t!
1s!
15!
1H
#120000
0!
0M
#125000
1!
1M
0#
0$
0O
0P
0x!
0t!
0s!
05!
0H
1$"
1_!
b1 5"
#130000
0!
0M
#135000
1!
1M
0$"
b1 4"
0_!
1k!
10"
b10 5"
1m!
#140000
0!
0M
